chameleon_fetcher.py
chameleon_fetcher-0.0.2.dist-info/LICENSE
chameleon_fetcher-0.0.2.dist-info/METADATA
chameleon_fetcher-0.0.2.dist-info/WHEEL
chameleon_fetcher-0.0.2.dist-info/top_level.txt
chameleon_fetcher-0.0.2.dist-info/RECORD
