Metadata-Version: 2.1
Name: chameleon-fetcher
Version: 0.0.2
Summary: Utility to quickly fetch and render a chameleon template
Home-page: https://github.com/jhb/chameleon_fetcher
Author: Joerg Baach
Author-email: mail@baach.de
Classifier: Programming Language :: Python :: 3
Classifier: License :: OSI Approved :: GNU General Public License v3 (GPLv3)
Classifier: Operating System :: OS Independent
Requires-Python: >=3.6
License-File: LICENSE
Requires-Dist: Chameleon
Provides-Extra: tests
Requires-Dist: pytest ; extra == 'tests'
